subnetcalc/__init__.py
subnetcalc/subnetcalc.py
subnetcalc-1.0.0.dist-info/METADATA
subnetcalc-1.0.0.dist-info/WHEEL
subnetcalc-1.0.0.dist-info/top_level.txt
subnetcalc-1.0.0.dist-info/RECORD
