Metadata-Version: 2.4
Name: subnetcalc
Version: 1.0.0
Summary: A lightweight and efficient Python tool to perform subnetting operations on IPv4 addresses. It can be used both as a standalone CLI utility and as a reusable module in your Python projects.
Home-page: https://github.com/recuer0
Author: recuero
Dynamic: author
Dynamic: description
Dynamic: description-content-type
Dynamic: home-page
Dynamic: summary
